fastioc/__init__.py
fastioc/container.py
fastioc/definitions.py
fastioc/errors.py
fastioc/integrations.py
fastioc/py.typed
fastioc/utils.py
fastioc/controller/__init__.py
fastioc/controller/controller.py
fastioc/controller/definitions.py
fastioc-0.2.0.dist-info/licenses/LICENSE.md
fastioc-0.2.0.dist-info/METADATA
fastioc-0.2.0.dist-info/WHEEL
fastioc-0.2.0.dist-info/top_level.txt
fastioc-0.2.0.dist-info/RECORD
