Metadata-Version: 2.4
Name: FastIoC
Version: 0.2.0
Summary: IoC/DI container for FastAPI with automatic type-based dependency injection
Author-email: "Amir R. Aliakbari" <OpenMindAmir@gmail.com>
License-Expression: MIT
Project-URL: Documentation, https://OpenMindAmir.github.io/FastIoC
Project-URL: GitHub, https://github.com/OpenMindAmir/FastIoC
Project-URL: Donation, https://OpenMindAmir.ir/donate
Requires-Python: >=3.12
License-File: LICENSE.md
Requires-Dist: fastapi>=0.116.1
Requires-Dist: fastapi-controllers>=0.3.0
Requires-Dist: typeguard>=4.4.4
Dynamic: license-file
